{"ProjectBreakpoints":"{\"Value\":{\"Process.xaml\":[{\"ConditionalExpression\":null,\"ActionExpression\":null,\"ExpectedHitCounter\":null,\"ShouldContinueAfterAction\":false,\"IsEnabled\":true,\"ActivityIdRef\":\"InvokeWorkflowFile_4\",\"ActivityId\":\"1.63\",\"ActivityName\":\"Invoke Workflow File\"},{\"ConditionalExpression\":null,\"ActionExpression\":null,\"ExpectedHitCounter\":null,\"ShouldContinueAfterAction\":false,\"IsEnabled\":true,\"ActivityIdRef\":\"InvokeWorkflowFile_3\",\"ActivityId\":\"1.5\",\"ActivityName\":\"Invoke Add data to queue workflow\"}],\"Tests/Add data to queue.xaml\":[{\"ConditionalExpression\":null,\"ActionExpression\":null,\"ExpectedHitCounter\":null,\"ShouldContinueAfterAction\":false,\"IsEnabled\":true,\"ActivityIdRef\":\"AddQueueItem_2\",\"ActivityId\":\"1.14\",\"ActivityName\":\"Add Queue Item\"}]}}","ProjectWatches":"{\"Value\":[{\"Id\":\"6deadb4d-7b91-4072-b48c-4edd665f12d5\",\"Expression\":\"out_ClientName\"},{\"Id\":\"bdb6eae1-ba70-4194-8033-04f83e2ffc8d\",\"Expression\":\"out_ProductName\"},{\"Id\":\"c407ed8f-20fa-4dcc-83fc-d5af7c91d0da\",\"Expression\":\"in_C\"},{\"Id\":\"2fd733ce-96b7-44a2-88bd-118ba2435e2a\",\"Expression\":\"in_P\"},{\"Id\":\"ef6151ab-4ddb-492e-9b86-e3fad499ada1\",\"Expression\":\"dt_ProductName\"},{\"Id\":\"02eb0d5a-ab62-4464-bf6d-e89f0e5e7479\",\"Expression\":\"var_ProductName\"}]}","OpenedDocuments":"[\"Framework/GetTransactionData.xaml\",\"Process Files/Validate Mandatory Fields.xaml\",\"Framework/InitAllSettings.xaml\",\"Tests/Add data to queue.xaml\",\"Process.xaml\",\"Main.xaml\",\"Get Data From DB(Autosaved).xaml\"]","LibraryProjectSettings":"{\"IncludeSourcesByDefault\":true,\"UseCompilerV2\":false,\"CompileExpressions\":true,\"DefaultActivitiesRootCategories\":[null]}"}